flet_flashlight/__init__.py
flet_flashlight/flashlight.py
flet_flashlight-0.80.5.dist-info/licenses/LICENSE
flutter/flet_flashlight/analysis_options.yaml
flutter/flet_flashlight/pubspec.lock
flutter/flet_flashlight/pubspec.yaml
flutter/flet_flashlight/lib/flet_flashlight.dart
flutter/flet_flashlight/lib/src/extension.dart
flutter/flet_flashlight/lib/src/flashlight.dart
flet_flashlight-0.80.5.dist-info/METADATA
flet_flashlight-0.80.5.dist-info/WHEEL
flet_flashlight-0.80.5.dist-info/top_level.txt
flet_flashlight-0.80.5.dist-info/RECORD
