Metadata-Version: 2.4
Name: flet-flashlight
Version: 0.80.5
Summary: Control device torch/flashlight from Flet apps.
Author-email: Flet contributors <hello@flet.dev>
License-Expression: Apache-2.0
Project-URL: Homepage, https://flet.dev
Project-URL: Documentation, https://docs.flet.dev/flashlight
Project-URL: Repository, https://github.com/flet-dev/flet/tree/main/sdk/python/packages/flet-flashlight
Project-URL: Issues, https://github.com/flet-dev/flet/issues
Requires-Python: >=3.10
License-File: LICENSE
Requires-Dist: flet==0.80.5
Dynamic: license-file
